README.txt
setup.py
collective/__init__.py
collective.portlet.manualRelated.egg-info/PKG-INFO
collective.portlet.manualRelated.egg-info/SOURCES.txt
collective.portlet.manualRelated.egg-info/dependency_links.txt
collective.portlet.manualRelated.egg-info/entry_points.txt
collective.portlet.manualRelated.egg-info/namespace_packages.txt
collective.portlet.manualRelated.egg-info/not-zip-safe
collective.portlet.manualRelated.egg-info/requires.txt
collective.portlet.manualRelated.egg-info/top_level.txt
collective/portlet/__init__.py
collective/portlet/manualRelated/__init__.py
collective/portlet/manualRelated/configure.zcml
collective/portlet/manualRelated/manualrelatedportlet.pt
collective/portlet/manualRelated/manualrelatedportlet.py
collective/portlet/manualRelated/version.txt
collective/portlet/manualRelated/profiles/default/metadata.xml
collective/portlet/manualRelated/profiles/default/portlets.xml
collective/portlet/manualRelated/tests/__init__.py
collective/portlet/manualRelated/tests/base.py
collective/portlet/manualRelated/tests/test_portlet.py
docs/HISTORY.txt
docs/INSTALL.txt
docs/LICENSE.GPL
docs/LICENSE.txt