Metadata-Version: 1.0
Name: collective.portlet.manualRelated
Version: 0.1
Summary: Portlet that shows items from manually related collections or folders
Home-page: http://svn.plone.org/svn/collective/
Author: David Jonas
Author-email: davidjonasdesign@gmail.com
License: GPL
Keywords: portlet related items manually series grouping categorizing
Platform: UNKNOWN
Classifier: Framework :: Plone
Classifier: Programming Language :: Python
